yodi/Yodi.py
yodi/__init__.py
yodi_pack-0.3.1.dist-info/LICENSE
yodi_pack-0.3.1.dist-info/METADATA
yodi_pack-0.3.1.dist-info/WHEEL
yodi_pack-0.3.1.dist-info/top_level.txt
yodi_pack-0.3.1.dist-info/RECORD
