Metadata-Version: 2.1
Name: yodi_pack
Version: 0.3.1
License-File: LICENSE
